LICENSE
MANIFEST.in
README
setup.py
yupp.pth
yupp/__init__.py
yupp/__main__.py
yupp.egg-info/PKG-INFO
yupp.egg-info/SOURCES.txt
yupp.egg-info/dependency_links.txt
yupp.egg-info/entry_points.txt
yupp.egg-info/not-zip-safe
yupp.egg-info/requires.txt
yupp.egg-info/top_level.txt
yupp/lib/corolib.yu
yupp/lib/coroutine-h.yu
yupp/lib/coroutine-py.yu
yupp/lib/coroutine.h
yupp/lib/coroutine.yu
yupp/lib/h-light.yu
yupp/lib/h.yu
yupp/lib/hlib.yu
yupp/lib/stdlib.yu
yupp/pp/__init__.py
yupp/pp/yuconfig.py
yupp/pp/yugen.py
yupp/pp/yulic.py
yupp/pp/yup.py
yupp/pylib/__init__.py
yupp/pylib/yutraceback.py
yupp/pylib/yutraceback2.py
yupp/pylib/yutraceback3.py