Metadata-Version: 1.1
Name: yupp
Version: 1.2rc1
Summary: yet another lexical preprocessor
Home-page: http://github.com/in4lio/yupp/
Author: Vitaly Kravtsov
Author-email: in4lio@gmail.com
License: MIT
Platform: any
Classifier: Development Status :: 5 - Production/Stable
Classifier: Environment :: Console
Classifier: Intended Audience :: Developers
Classifier: License :: OSI Approved :: MIT License
Classifier: Operating System :: OS Independent
Classifier: Programming Language :: Python
